spyglass/app.py
spyglass/database.py
spyglass/utils.py
spyglass/__pycache__/database.cpython-311.pyc
spyglass/__pycache__/database.cpython-312.pyc
spyglass/__pycache__/utils.cpython-311.pyc
spyglass/__pycache__/utils.cpython-312.pyc
spyglass_cli-0.1.2.dist-info/LICENSE
spyglass_cli-0.1.2.dist-info/METADATA
spyglass_cli-0.1.2.dist-info/WHEEL
spyglass_cli-0.1.2.dist-info/entry_points.txt
spyglass_cli-0.1.2.dist-info/top_level.txt
spyglass_cli-0.1.2.dist-info/RECORD
